{
   "path": [
      {
         "zone": "arathi",
         "experience": 40.61,
         "waypoints": [
            {
               "coords": { "x": 46, "y": 46 },
               "align": "top",
               "header": "Refuge Point",
               "starts": [["Trelane's Defenses", "E"], ["Wanted: Marez Cowl", "E"], ["Wanted: Otto and Falconcrest", "E"], ["Stromgarde Badges", "E"]],
               "type": "hub"
            },
            {
               "coords": { "x": 67, "y": 36 },
               "align": "top",
               "header": "Fozruk Spawn Point",
               "objectives": [["Breaking the Keystone", "E"]],
               "type": "objective"
            },
            {
               "coords": { "x": 36, "y": 58 },
               "align": "top",
               "header": "Keystone Monument",
               "ends": [["Breaking the Keystone", "E"]],
               "starts": ["Myzrael's Allies"],
               "type": "quest"
            },
            {
               "coords": { "x": 30, "y": 63 },
               "align": "top",
               "header": "Eastern Stromgarde",
               "objectives": [["Wanted: Marez Cowl", "E"], ["Stromgarde Badges", "E"]],
               "type": "objective"
            },
            {
               "coords": { "x": 26, "y": 66 },
               "align": "top",
               "header": "Stromgarde Keep",
               "objectives": [["Wanted: Otto and Falconcrest", "E"], ["Stromgarde Badges", "E"]],
               "type": "objective"
            },
            {
               "coords": { "x": 21, "y": 68 },
               "align": "top",
               "header": "Western Stromgarde",
               "objectives": [["Trelane's Defenses", "E"]],
               "special": ["Kill Ogre Shamans"],
               "type": "objective"
            }
         ]
      },
      {
         "zone": "arathi",
         "experience": 40.76,
         "waypoints": [
            {
               "coords": { "x": 21, "y": 68 },
               "align": "top",
               "header": "Western Stromgarde",
               "objectives": [["Trelane's Defenses", "E"]],
               "special": ["Kill Ogre Shamans"],
               "type": "objective"
            },
            {
               "coords": { "x": 46, "y": 46 },
               "align": "top",
               "header": "Refuge Point",
               "ends": [["Trelane's Defenses", "E"], ["Wanted: Marez Cowl", "E"], ["Wanted: Otto and Falconcrest", "E"], ["Stromgarde Badges", "E"], "An Apprentice's Enchantment"],
               "starts": ["An Apprentice's Enchantment", ["Attack on the Tower", "E"]],
               "type": "hub"
            }
         ]
      },
      {
         "zone": "arathi",
         "experience": 40.91,
         "waypoints": [
            {
               "coords": { "x": 46, "y": 46 },
               "align": "top",
               "header": "Refuge Point",
               "type": "hub"
            },
            {
               "coords": { "x": 18, "y": 68 },
               "header": "Stromgarde Tower",
               "objectives": ["Attack on the Tower"],
               "special": ["Loot the three lockboxes"],
               "type": "objective"
            },
            {
               "coords": { "x": 26, "y": 54 },
               "header": "Move Here",
               "type": "travel"
            },
            {
               "coords": { "x": 31, "y": 65 },
               "align": "right",
               "header": "Move Here",
               "type": "travel"
            },
            {
               "coords": { "x": 22, "y": 80 },
               "header": "Move Here",
               "type": "travel"
            },
            {
               "coords": { "x": 32, "y": 82 },
               "align": "right",
               "header": "Faldir's Cove",
               "ends": ["Land Ho!", ["Sunken Treasure", "P1"]],
               "starts": ["Land Ho!", "Deep Sea Salvage", "Drowned Sorrows", ["Sunken Treasure", "P1"], ["Sunken Treasure", "P2"]],
               "type": "quest"
            }
         ]
      },
      {
         "zone": "arathi",
         "experience": 40.95,
         "waypoints": [
            {
               "coords": { "x": 32, "y": 82 },
               "align": "right",
               "header": "Faldir's Cove",
               "ends": ["Land Ho!", ["Sunken Treasure", "P1"]],
               "starts": ["Land Ho!", "Deep Sea Salvage", "Drowned Sorrows", ["Sunken Treasure", "P1"], ["Sunken Treasure", "P2"]],
               "type": "quest"
            },
            {
               "coords": { "x": 22, "y": 89 },
               "align": "bottom",
               "header": "The Drowned Reef",
               "objectives": [["Sunken Treasure", "P2"], "Drowned Sorrows"],
               "type": "objective"
            },
            {
               "coords": { "x": 23, "y": 85 },
               "align": "top",
               "header": "Eastern Shipwreck",
               "objectives": ["Deep Sea Salvage"],
               "special": ["Youtube Video"],
               "type": "objective"
            },
            {
               "coords": { "x": 21, "y": 86 },
               "header": "Western Shipwreck",
               "objectives": ["Deep Sea Salvage"],
               "special": ["Youtube Video"],
               "type": "objective"
            }
         ]
      },
      {
         "zone": "arathi",
         "experience": 41.04,
         "waypoints": [
            {
               "coords": { "x": 21, "y": 86 },
               "align": "top",
               "header": "Western Shipwreck",
               "objectives": ["Deep Sea Salvage"],
               "special": ["Youtube Video"],
               "type": "objective"
            },
            {
               "coords": { "x": 32, "y": 82 },
               "align": "top",
               "header": "Faldir's Cove",
               "ends": ["Deep Sea Salvage", "Drowned Sorrows", ["Sunken Treasure", "P2-3"]],
               "starts": [["Sunken Treasure", "P3-4"]],
               "special": ["Hearthstone to Southshire"],
               "type": "quest"
            }
         ]
      }
   ]
}